cofunc/__init__.py
cofunc/changelog.md
cofunc-0.1.3.dist-info/METADATA
cofunc-0.1.3.dist-info/WHEEL
cofunc-0.1.3.dist-info/licenses/LICENSE.txt
cofunc-0.1.3.dist-info/RECORD
