Metadata-Version: 2.1
Name: cofunc
Version: 0.1.3
Summary: Implement a class whose instances hold discretized data representing continuous functions.
Project-URL: Source, https://github.com/proggy/cofunc
Project-URL: Homepage, https://github.com/proggy/cofunc
Project-URL: Bug Tracker, https://github.com/proggy/cofunc/issues
Author-email: Daniel Jung <proggy-contact@mailbox.org>
Maintainer-email: Daniel Jung <proggy-contact@mailbox.org>
License-File: LICENSE.txt
Classifier: License :: OSI Approved :: GNU General Public License v2 (GPLv2)
Classifier: Operating System :: OS Independent
Classifier: Programming Language :: Python :: 3
Requires-Python: >=3.7
Requires-Dist: scipy
